{
  "project_info": {
    "project_number": "1069735437208",
    "project_id": "shopping-flutter-57578",
    "storage_bucket": "shopping-flutter-57578.appspot.com"
  },
  "client": [
    {
      "client_info": {
        "mobilesdk_app_id": "1:1069735437208:android:19803af38640f392a701ed",
        "android_client_info": {
          "package_name": "com.shrikanta.shopping_flutter"
        }
      },
      "oauth_client": [
        {
          "client_id": "1069735437208-2g5vd0n0i5pcqgbefag0ntodbo80qc0h.apps.googleusercontent.com",
          "client_type": 3
        }
      ],
      "api_key": [
        {
          "current_key": "AIzaSyCh5YiqCvnOTz4_QGteABtE1qt6z2iFhjQ"
        }
      ],
      "services": {
        "appinvite_service": {
          "other_platform_oauth_client": [
            {
              "client_id": "1069735437208-2g5vd0n0i5pcqgbefag0ntodbo80qc0h.apps.googleusercontent.com",
              "client_type": 3
            }
          ]
        }
      }
    }
  ],
  "configuration_version": "1"
}